example.py
wocemaps.py
wocemaps-0.0.2.dist-info/.ipynb_checkpoints/PKG-INFO-checkpoint
wocemaps-0.0.2.dist-info/.ipynb_checkpoints/SOURCES-checkpoint.txt
wocemaps-0.0.2.dist-info/.ipynb_checkpoints/dependency_links-checkpoint.txt
wocemaps-0.0.2.dist-info/.ipynb_checkpoints/top_level-checkpoint.txt
wocemaps-0.0.2.dist-info/LICENSE
wocemaps-0.0.2.dist-info/METADATA
wocemaps-0.0.2.dist-info/WHEEL
wocemaps-0.0.2.dist-info/top_level.txt
wocemaps-0.0.2.dist-info/RECORD
